bvi_looting/__init__.py
bvi_looting/client.py
bvi_looting-0.1.6.dist-info/METADATA
bvi_looting-0.1.6.dist-info/WHEEL
bvi_looting-0.1.6.dist-info/top_level.txt
bvi_looting-0.1.6.dist-info/RECORD
