Metadata-Version: 2.4
Name: bvi-looting
Version: 0.1.6
Requires-Python: >=3.7
Requires-Dist: requests>=2.28
Requires-Dist: python-dotenv>=1.0
Provides-Extra: server
Requires-Dist: fastapi>=0.100; extra == "server"
Requires-Dist: uvicorn[standard]>=0.22; extra == "server"
Requires-Dist: google-genai>=1.0; extra == "server"
Requires-Dist: python-dotenv>=1.0; extra == "server"
